xensesdk/__compile__.cp310-win_amd64.pyd
xensesdk/__init__.py
xensesdk/__init__.pyi
xensesdk/__pycache__/__init__.cpython-310.opt-1.pyc
xensesdk/__pycache__/__init__.cpython-310.pyc
xensesdk/examples/example_data_processing.py
xensesdk/examples/example_depth.py
xensesdk/examples/example_finger_depth.py
xensesdk/examples/example_force.py
xensesdk/examples/example_marker_detect.py
xensesdk/examples/example_record_data.py
xensesdk/examples/example_remote_data.py
xensesdk/examples/example_save_and_replay.py
xensesdk/examples/__pycache__/example_data_processing.cpython-310.opt-1.pyc
xensesdk/examples/__pycache__/example_data_processing.cpython-310.pyc
xensesdk/examples/__pycache__/example_depth.cpython-310.opt-1.pyc
xensesdk/examples/__pycache__/example_depth.cpython-310.pyc
xensesdk/examples/__pycache__/example_finger_depth.cpython-310.opt-1.pyc
xensesdk/examples/__pycache__/example_finger_depth.cpython-310.pyc
xensesdk/examples/__pycache__/example_force.cpython-310.opt-1.pyc
xensesdk/examples/__pycache__/example_force.cpython-310.pyc
xensesdk/examples/__pycache__/example_marker_detect.cpython-310.opt-1.pyc
xensesdk/examples/__pycache__/example_marker_detect.cpython-310.pyc
xensesdk/examples/__pycache__/example_record_data.cpython-310.opt-1.pyc
xensesdk/examples/__pycache__/example_record_data.cpython-310.pyc
xensesdk/examples/__pycache__/example_remote_data.cpython-310.opt-1.pyc
xensesdk/examples/__pycache__/example_remote_data.cpython-310.pyc
xensesdk/examples/__pycache__/example_save_and_replay.cpython-310.opt-1.pyc
xensesdk/examples/__pycache__/example_save_and_replay.cpython-310.pyc
xensesdk/ezgl/__init__.py
xensesdk/ezgl/__pycache__/__init__.cpython-310.opt-1.pyc
xensesdk/ezgl/__pycache__/__init__.cpython-310.pyc
xensesdk/ezgl/experimental/__init__.py
xensesdk/ezgl/experimental/__pycache__/__init__.cpython-310.opt-1.pyc
xensesdk/ezgl/experimental/__pycache__/__init__.cpython-310.pyc
xensesdk/ezgl/items/__init__.py
xensesdk-1.6.5.dist-info/METADATA
xensesdk-1.6.5.dist-info/WHEEL
xensesdk-1.6.5.dist-info/entry_points.txt
xensesdk-1.6.5.dist-info/top_level.txt
xensesdk-1.6.5.dist-info/RECORD
