Metadata-Version: 2.4
Name: xensesdk
Version: 1.6.5
Summary: xense SDK for everything supported
Author: Hongzhan Yu
Author-email: yuhongzhan@xenserobotics.com
Classifier: Programming Language :: Python :: 3
Classifier: License :: OSI Approved :: MIT License
Classifier: Operating System :: OS Independent
Requires-Python: >=3.9
Requires-Dist: cypack
Requires-Dist: numpy<=1.26.4
Requires-Dist: opencv-python==4.10.0.84
Requires-Dist: PyOpenGL==3.1.7
Requires-Dist: assimp-py==1.0.7
Requires-Dist: pillow==10.2.0
Requires-Dist: PySide6
Requires-Dist: cryptography==43.0.3
Requires-Dist: PyYAML==6.0.2
Requires-Dist: qtpy
Requires-Dist: h5py
Requires-Dist: av==13.1.0
Requires-Dist: scipy==1.13.1
Requires-Dist: lz4
Requires-Dist: psutil>=5.9.0
Requires-Dist: wmi; platform_system == "Windows"
Requires-Dist: pyudev; platform_system == "Linux"
Requires-Dist: onnxruntime-gpu<=1.20
Requires-Dist: cyclonedds-nightly==2025.7.29
Provides-Extra: ant-ext
Requires-Dist: xensesdk-ant-ext>=1.0.0; extra == "ant-ext"
Dynamic: author
Dynamic: author-email
Dynamic: classifier
Dynamic: provides-extra
Dynamic: requires-dist
Dynamic: requires-python
Dynamic: summary
